main.py
agent/agent.py
agent/events.py
agent/session.py
agent/state.py
client/llm_client.py
client/response.py
config/config.py
config/loader.py
context/compaction.py
context/loop_detector.py
context/manager.py
hooks/hook_system.py
prompts/system.py
safety/approval.py
tools/base.py
tools/discovery.py
tools/registry.py
tools/subagent.py
tools/builtin/__init__.py
tools/builtin/edit_file.py
tools/builtin/glob.py
tools/builtin/grep.py
tools/builtin/list_dir.py
tools/builtin/memory.py
tools/builtin/read_file.py
tools/builtin/shell.py
tools/builtin/todo.py
tools/builtin/web_fetch.py
tools/builtin/web_search.py
tools/builtin/write_file.py
tools/mcp/client.py
tools/mcp/mcp_manager.py
tools/mcp/mcp_tool.py
ui/tui.py
utils/errors.py
utils/paths.py
utils/text.py
simhacli-1.0.3.dist-info/METADATA
simhacli-1.0.3.dist-info/WHEEL
simhacli-1.0.3.dist-info/entry_points.txt
simhacli-1.0.3.dist-info/top_level.txt
simhacli-1.0.3.dist-info/RECORD
