Metadata-Version: 2.4
Name: simhacli
Version: 1.0.3
Summary: SimhaCLI 🦁 — AI Coding Agent that runs inside your terminal
Author: Narasimha Naidu Korrapti
License: MIT
Project-URL: Homepage, https://github.com/naidu199/SimhaCLI
Project-URL: Repository, https://github.com/naidu199/SimhaCLI
Keywords: ai,cli,agent,coding,llm,terminal
Classifier: Development Status :: 4 - Beta
Classifier: Environment :: Console
Classifier: Intended Audience :: Developers
Classifier: License :: OSI Approved :: MIT License
Classifier: Operating System :: OS Independent
Classifier: Programming Language :: Python :: 3
Classifier: Programming Language :: Python :: 3.10
Classifier: Programming Language :: Python :: 3.11
Classifier: Programming Language :: Python :: 3.12
Classifier: Topic :: Software Development :: Code Generators
Classifier: Topic :: Utilities
Requires-Python: >=3.10
Requires-Dist: click>=8.0.0
Requires-Dist: rich>=13.0.0
Requires-Dist: httpx>=0.25.0
Requires-Dist: anyio>=4.0.0
Requires-Dist: pydantic>=2.0.0
Requires-Dist: toml>=0.10.0
Requires-Dist: tomli-w>=1.0.0
Requires-Dist: ddgs>=6.0.0
Requires-Dist: fastmcp>=2.0.0
Requires-Dist: diskcache>=5.0.0
Requires-Dist: openai>=1.0.0
Requires-Dist: tiktoken>=0.5.0
Requires-Dist: platformdirs>=3.0.0
